sermos_tools/__init__.py
sermos_tools/constants.py
sermos_tools/sermos_tools.py
sermos_tools/catalog/__init__.py
sermos_tools/catalog/date_extractor/__init__.py
sermos_tools/catalog/date_extractor/date_extractor.py
sermos_tools/catalog/date_extractor/requirements.txt
sermos_tools/catalog/date_extractor/test_date_extractor.py
sermos_tools/catalog/document_classifier/__init__.py
sermos_tools/catalog/document_classifier/document_classifier.py
sermos_tools/catalog/document_classifier/requirements.txt
sermos_tools/catalog/document_classifier/test_document_classifier.py
sermos_tools/catalog/hasher/__init__.py
sermos_tools/catalog/hasher/hasher.py
sermos_tools/catalog/hasher/requirements.txt
sermos_tools/catalog/hasher/test_hasher.py
sermos_tools/catalog/language_detector/__init__.py
sermos_tools/catalog/language_detector/language_detector.py
sermos_tools/catalog/language_detector/requirements.txt
sermos_tools/catalog/language_detector/test_language_detector.py
sermos_tools/catalog/slack_notifier/__init__.py
sermos_tools/catalog/slack_notifier/requirements.txt
sermos_tools/catalog/slack_notifier/slack_notifier.py
sermos_tools/catalog/slack_notifier/test_slack_notifier.py
sermos_tools/catalog/sparse_embedding_search/__init__.py
sermos_tools/catalog/sparse_embedding_search/requirements.txt
sermos_tools/catalog/sparse_embedding_search/sparse_embedding_search.py
sermos_tools/catalog/sparse_embedding_search/test_tools_embedding_search.py
sermos_tools/catalog/text_extractor/__init__.py
sermos_tools/catalog/text_extractor/requirements.txt
sermos_tools/catalog/text_extractor/test_text_extractor.py
sermos_tools/catalog/text_extractor/text_extractor.py
sermos_tools/catalog/tfidf_vectorizer/__init__.py
sermos_tools/catalog/tfidf_vectorizer/requirements.txt
sermos_tools/catalog/tfidf_vectorizer/test_tfidf_vectorizer.py
sermos_tools/catalog/tfidf_vectorizer/tfidf_vectorizer.py
sermos_tools/catalog/thumbnail_generator/__init__.py
sermos_tools-0.4.3.dist-info/LICENSE
sermos_tools-0.4.3.dist-info/METADATA
sermos_tools-0.4.3.dist-info/WHEEL
sermos_tools-0.4.3.dist-info/top_level.txt
sermos_tools-0.4.3.dist-info/RECORD
