Metadata-Version: 2.1
Name: sermos-tools
Version: 0.4.3
Summary: Sermos Tools
Home-page: https://gitlab.com/sermos/sermos-tools
Maintainer: Sermos, LLC
License: Apache License 2.0
Platform: UNKNOWN
Provides-Extra: build
Requires-Dist: twine ; extra == 'build'
Requires-Dist: wheel ; extra == 'build'
Provides-Extra: date_extractor
Requires-Dist: regex (==2019.11.1) ; extra == 'date_extractor'
Requires-Dist: cytoolz (<0.11,>=0.10.1) ; extra == 'date_extractor'
Provides-Extra: dev
Requires-Dist: honcho ; extra == 'dev'
Provides-Extra: docs
Requires-Dist: sphinx (<4,>=3.0.2) ; extra == 'docs'
Requires-Dist: boto3 (<2,>=1.11) ; extra == 'docs'
Provides-Extra: document_classifier
Requires-Dist: sklearn ; extra == 'document_classifier'
Requires-Dist: scipy ; extra == 'document_classifier'
Requires-Dist: cytoolz ; extra == 'document_classifier'
Requires-Dist: rho-ml ; extra == 'document_classifier'
Requires-Dist: attr ; extra == 'document_classifier'
Requires-Dist: requests ; extra == 'document_classifier'
Requires-Dist: boto3 ; extra == 'document_classifier'
Requires-Dist: xgboost ; extra == 'document_classifier'
Provides-Extra: hasher
Provides-Extra: language_detector
Requires-Dist: langdetect (<1.1,>=1.0.7) ; extra == 'language_detector'
Provides-Extra: slack_notifier
Requires-Dist: attrs (<20,>=19) ; extra == 'slack_notifier'
Requires-Dist: requests (>=2.24.0) ; extra == 'slack_notifier'
Provides-Extra: sparse_embedding_search
Requires-Dist: rho-pysparnn (>=0.4.1) ; extra == 'sparse_embedding_search'
Requires-Dist: rho-ml (>=0.10.0) ; extra == 'sparse_embedding_search'
Requires-Dist: requests (>=2.24.0) ; extra == 'sparse_embedding_search'
Requires-Dist: boto3 (<2,>=1.11) ; extra == 'sparse_embedding_search'
Provides-Extra: test
Requires-Dist: pytest-cov (<3,>=2.6.1) ; extra == 'test'
Requires-Dist: tox (<4,>=3.14.1) ; extra == 'test'
Requires-Dist: coverage (<5,>=4.5) ; extra == 'test'
Requires-Dist: mock (<2,>=1) ; extra == 'test'
Provides-Extra: test-ci
Requires-Dist: tox (<4,>=3.14.1) ; extra == 'test-ci'
Provides-Extra: text_extractor
Requires-Dist: python-magic (<1.0.0,>=0.4.15) ; extra == 'text_extractor'
Requires-Dist: pdftotext (<3.0.0,>=2.1.1) ; extra == 'text_extractor'
Requires-Dist: beautifulsoup4 (<5.0.0,>=4.6.3) ; extra == 'text_extractor'
Provides-Extra: tfidf_vectorizer
Requires-Dist: sklearn ; extra == 'tfidf_vectorizer'
Requires-Dist: scipy ; extra == 'tfidf_vectorizer'
Requires-Dist: cytoolz ; extra == 'tfidf_vectorizer'
Requires-Dist: rho-ml ; extra == 'tfidf_vectorizer'
Requires-Dist: attr ; extra == 'tfidf_vectorizer'
Requires-Dist: requests ; extra == 'tfidf_vectorizer'
Requires-Dist: boto3 ; extra == 'tfidf_vectorizer'
Provides-Extra: thumbnail_generator
Requires-Dist: python-magic (<1.0.0,>=0.4.15) ; extra == 'thumbnail_generator'
Requires-Dist: pdf2image (<1.12,>=1.9.0) ; extra == 'thumbnail_generator'
Requires-Dist: boto3 (<2,>=1.11) ; extra == 'thumbnail_generator'
